georef_ar_address/__init__.py
georef_ar_address/__main__.py
georef_ar_address/address_data.py
georef_ar_address/address_parser.py
georef_ar_address/grammars/address-ar.cfg
georef_ar_address-0.0.10.dist-info/licenses/LICENSE
georef_ar_address-0.0.10.dist-info/METADATA
georef_ar_address-0.0.10.dist-info/WHEEL
georef_ar_address-0.0.10.dist-info/top_level.txt
georef_ar_address-0.0.10.dist-info/RECORD
