Metadata-Version: 2.4
Name: georef-ar-address
Version: 0.0.10
Summary: Librería escrita en Python para la identificación de componentes de direcciones argentinas
Author-email: Datos Argentina <datosargentina@jefatura.gob.ar>
License: MIT
Project-URL: Homepage, https://github.com/datosgobar/georef-ar-address
Project-URL: Download, https://github.com/datosgobar/georef-ar-address/archive/0.0.10.tar.gz
Keywords: georef,datos,argentina,direccion,calle,altura,json,nltk
Classifier: Programming Language :: Python :: 3 :: Only
Classifier: License :: OSI Approved :: MIT License
Classifier: Topic :: Text Processing
Classifier: Topic :: Software Development :: Libraries
Requires-Python: >=3
License-File: LICENSE
Requires-Dist: nltk==3.5
Provides-Extra: dev
Requires-Dist: pylint==2.3.1; extra == "dev"
Requires-Dist: flake8==3.6.0; extra == "dev"
Requires-Dist: twine==1.12.1; extra == "dev"
Requires-Dist: coverage==4.5.2; extra == "dev"
Requires-Dist: coveralls==1.5.1; extra == "dev"
Dynamic: license-file
